{
   "display":{
      "description":"",
      "title":"",
      "show_toast":false,
      "announce_to_chat":false,
      "background":"minecraft:textures/blocks/stone.png",
      "icon":{
         "item":"chest"
      }
   },
   "criteria":{
      "inv_changed-chest":{
         "trigger":"minecraft:inventory_changed",
         "conditions":{
            "items":[
               {
                  "item":"chest"
               }
            ]
         }
      }
   },
   "rewards":{
      "recipes":[
      	 "toms_storage:inventory_cable_framed",
      	 "toms_storage:inventory_hopper_basic",
         "toms_storage:inventory_cable",
         "toms_storage:inventory_proxy",
         "toms_storage:open_crate",
         "toms_storage:paint_kit",
         "toms_storage:trim_clean",
         "toms_storage:trim"
      ]
   },
   "requirements":[
      [
         "inv_changed-chest"
      ]
   ]
}