{
  "multipart": [
    {
      "apply": {
        "model": "toms_storage:block/cable_framed"
      }
    },
    {
      "apply": {
        "uvlock": "true",
        "x": 90,
        "model": "toms_storage:block/cable_closed"
      },
      "when": {
        "down": "false"
      }
    },
    {
      "apply": {
        "uvlock": "true",
        "x": 90,
        "model": "toms_storage:block/cable_open"
      },
      "when": {
        "down": "true"
      }
    },
    {
      "apply": {
        "uvlock": "true",
        "x": -90,
        "model": "toms_storage:block/cable_closed"
      },
      "when": {
        "up": "false"
      }
    },
    {
      "apply": {
        "uvlock": "true",
        "x": -90,
        "model": "toms_storage:block/cable_open"
      },
      "when": {
        "up": "true"
      }
    },
    {
      "apply": {
        "uvlock": "true",
        "model": "toms_storage:block/cable_closed"
      },
      "when": {
        "north": "false"
      }
    },
    {
      "apply": {
        "uvlock": "true",
        "model": "toms_storage:block/cable_open"
      },
      "when": {
        "north": "true"
      }
    },
    {
      "apply": {
        "uvlock": "true",
        "y": 180,
        "model": "toms_storage:block/cable_closed"
      },
      "when": {
        "south": "false"
      }
    },
    {
      "apply": {
        "uvlock": "true",
        "y": 180,
        "model": "toms_storage:block/cable_open"
      },
      "when": {
        "south": "true"
      }
    },
    {
      "apply": {
        "uvlock": "true",
        "y": 270,
        "model": "toms_storage:block/cable_closed"
      },
      "when": {
        "west": "false"
      }
    },
    {
      "apply": {
        "uvlock": "true",
        "y": 270,
        "model": "toms_storage:block/cable_open"
      },
      "when": {
        "west": "true"
      }
    },
    {
      "apply": {
        "uvlock": "true",
        "y": 90,
        "model": "toms_storage:block/cable_closed"
      },
      "when": {
        "east": "false"
      }
    },
    {
      "apply": {
        "uvlock": "true",
        "y": 90,
        "model": "toms_storage:block/cable_open"
      },
      "when": {
        "east": "true"
      }
    },
    {
      "apply": {
        "x": 90,
        "model": "toms_storage:block/cable_connector/base"
      },
      "when": {
        "facing": "down"
      }
    },
    {
      "apply": {
        "x": 90,
        "model": "toms_storage:block/cable_connector/ext"
      },
      "when": {
        "facing": "down",
        "down": "true"
      }
    },
    {
      "apply": {
        "x": -90,
        "model": "toms_storage:block/cable_connector/base"
      },
      "when": {
        "facing": "up"
      }
    },
    {
      "apply": {
        "x": -90,
        "model": "toms_storage:block/cable_connector/ext"
      },
      "when": {
        "facing": "up",
        "up": "true"
      }
    },
    {
      "apply": {
        "model": "toms_storage:block/cable_connector/base"
      },
      "when": {
        "facing": "north"
      }
    },
    {
      "apply": {
        "model": "toms_storage:block/cable_connector/ext"
      },
      "when": {
        "north": "true",
        "facing": "north"
      }
    },
    {
      "apply": {
        "y": 180,
        "model": "toms_storage:block/cable_connector/base"
      },
      "when": {
        "facing": "south"
      }
    },
    {
      "apply": {
        "y": 180,
        "model": "toms_storage:block/cable_connector/ext"
      },
      "when": {
        "south": "true",
        "facing": "south"
      }
    },
    {
      "apply": {
        "y": 270,
        "model": "toms_storage:block/cable_connector/base"
      },
      "when": {
        "facing": "west"
      }
    },
    {
      "apply": {
        "y": 270,
        "model": "toms_storage:block/cable_connector/ext"
      },
      "when": {
        "west": "true",
        "facing": "west"
      }
    },
    {
      "apply": {
        "y": 90,
        "model": "toms_storage:block/cable_connector/base"
      },
      "when": {
        "facing": "east"
      }
    },
    {
      "apply": {
        "y": 90,
        "model": "toms_storage:block/cable_connector/ext"
      },
      "when": {
        "east": "true",
        "facing": "east"
      }
    }
  ]
}